mytec/__init__.py
mytec/bin/__init__.py
mytec/bin/cli.py
mytec/cli/__init__.py
mytec/cli/app.py
mytec/cli/venv.py
mytec-0.1.0.dist-info/entry_points.txt
mytec-0.1.0.dist-info/METADATA
mytec-0.1.0.dist-info/WHEEL
mytec-0.1.0.dist-info/RECORD
